kindel/__init__.py
kindel/cli.py
kindel/kindel.py
kindel-1.2.0.dist-info/entry_points.txt
kindel-1.2.0.dist-info/LICENSE
kindel-1.2.0.dist-info/WHEEL
kindel-1.2.0.dist-info/METADATA
kindel-1.2.0.dist-info/RECORD
