Metadata-Version: 2.3
Name: kindel
Version: 1.2.0
Summary: Indel-aware consensus from aligned BAMs
Author-email: Bede Constantinides <bedeabc@gmail.com>
Requires-Python: >=3.8
Classifier: Environment :: Console
Classifier: Intended Audience :: Science/Research
Classifier: License :: OSI Approved :: GNU General Public License v3 (GPLv3)
Classifier: Natural Language :: English
Classifier: Operating System :: POSIX :: Linux
Classifier: Operating System :: MacOS :: MacOS X
Classifier: Programming Language :: Python :: 3.9
Classifier: Programming Language :: Python :: 3.13
Classifier: Topic :: Scientific/Engineering :: Bio-Informatics
Requires-Dist: argh>=0.26.2
Requires-Dist: tqdm>=4.11.2
Requires-Dist: scipy>=0.19.0
Requires-Dist: pandas>=0.19.2
Requires-Dist: dnaio==1.2.3
Requires-Dist: simplesam==0.1.3.2
Requires-Dist: plotly>=2.0.0
Requires-Dist: pytest ; extra == "dev"
Requires-Dist: pre-commit ; extra == "dev"
Requires-Dist: pytest-cov ; extra == "dev"
Requires-Dist: flit ; extra == "dev"
Project-URL: Homepage, https://github.com/bede/kindel
Provides-Extra: dev
